mixician/__init__.py
mixcian-0.0.1.dist-info/LICENSE
mixcian-0.0.1.dist-info/METADATA
mixcian-0.0.1.dist-info/WHEEL
mixcian-0.0.1.dist-info/top_level.txt
mixcian-0.0.1.dist-info/RECORD
