Metadata-Version: 2.1
Name: mixcian
Version: 0.0.1
Summary: An advanced hybrid ranking engine for recommendation systems, designed to automate the optimization of algorithms and parameters tailored to diverse business objectives.
Home-page: https://github.com/yinsn/Mixcian
Author: Yin Cheng
Author-email: yin.sjtu@gmail.com
Requires-Python: >=3.6
License-File: LICENSE
Requires-Dist: jax >=0.4.14
Requires-Dist: numpyro >=0.12.0
